quasselconf
